pseudol10nutil/__init__.py
pseudol10nutil/pseudol10nutil.py
pseudol10nutil/transforms.py
pseudol10nutil-0.1.dev5.dist-info/METADATA
pseudol10nutil-0.1.dev5.dist-info/RECORD
pseudol10nutil-0.1.dev5.dist-info/WHEEL
pseudol10nutil-0.1.dev5.dist-info/top_level.txt
