Metadata-Version: 2.1
Name: pseudol10nutil
Version: 0.1.dev5
Summary: Classes and functions for performing pseudo-localization on strings and PO files.
Home-page: https://github.com/leonidessaguisagjr/pseudol10nutil
Author: Leonides T. Saguisag Jr.
Author-email: leonidessaguisagjr@gmail.com
License: MIT
Platform: UNKNOWN
Classifier: Development Status :: 3 - Alpha
Classifier: Intended Audience :: Developers
Classifier: License :: OSI Approved :: MIT License
Classifier: Programming Language :: Python
Classifier: Programming Language :: Python :: 2
Classifier: Programming Language :: Python :: 2.7
Classifier: Programming Language :: Python :: 3
Classifier: Programming Language :: Python :: 3.6
Classifier: Topic :: Software Development :: Libraries
Classifier: Topic :: Software Development :: Localization
Classifier: Topic :: Text Processing
Classifier: Topic :: Text Processing :: Linguistic
Requires-Dist: six
